arp_standard_server/__init__.py
arp_standard_server/app.py
arp_standard_server/auth.py
arp_standard_server/errors.py
arp_standard_server/py.typed
arp_standard_server/atomic_executor/__init__.py
arp_standard_server/atomic_executor/router.py
arp_standard_server/atomic_executor/server.py
arp_standard_server/composite_executor/__init__.py
arp_standard_server/composite_executor/router.py
arp_standard_server/composite_executor/server.py
arp_standard_server/node_registry/__init__.py
arp_standard_server/node_registry/router.py
arp_standard_server/node_registry/server.py
arp_standard_server/pdp/__init__.py
arp_standard_server/pdp/router.py
arp_standard_server/pdp/server.py
arp_standard_server/run_coordinator/__init__.py
arp_standard_server/run_coordinator/router.py
arp_standard_server/run_coordinator/server.py
arp_standard_server/run_gateway/__init__.py
arp_standard_server/run_gateway/router.py
arp_standard_server/run_gateway/server.py
arp_standard_server/selection/__init__.py
arp_standard_server/selection/router.py
arp_standard_server/selection/server.py
arp_standard_server-0.3.7.dist-info/licenses/LICENSE
arp_standard_server-0.3.7.dist-info/METADATA
arp_standard_server-0.3.7.dist-info/WHEEL
arp_standard_server-0.3.7.dist-info/top_level.txt
arp_standard_server-0.3.7.dist-info/RECORD
