Metadata-Version: 2.4
Name: arp-standard-server
Version: 0.3.7
Summary: FastAPI server scaffolding for the ARP Standard (v1).
Author: Agent Runtime Protocol
License-Expression: MIT
Project-URL: Repository, https://github.com/AgentRuntimeProtocol/ARP_Standard
Project-URL: Issues, https://github.com/AgentRuntimeProtocol/ARP_Standard/issues
Requires-Python: >=3.11
License-File: LICENSE
Requires-Dist: fastapi>=0.110.0
Requires-Dist: PyJWT[crypto]>=2.8.0
Requires-Dist: arp-standard-model==0.3.7
Provides-Extra: dev
Requires-Dist: pyright>=1.1.0; extra == "dev"
Requires-Dist: pytest>=7; extra == "dev"
Dynamic: license-file
